seraph_clicker_hyaku/__init__.py
seraph_clicker_hyaku/main.py
seraph_clicker_hyaku-0.0.3.dist-info/LICENSE
seraph_clicker_hyaku-0.0.3.dist-info/METADATA
seraph_clicker_hyaku-0.0.3.dist-info/WHEEL
seraph_clicker_hyaku-0.0.3.dist-info/top_level.txt
seraph_clicker_hyaku-0.0.3.dist-info/RECORD
