Metadata-Version: 2.1
Name: seraph_clicker_hyaku
Version: 0.0.3
Summary: Just an autoclicker
Author: Hyaku
Classifier: Programming Language :: Python :: 3
Classifier: License :: OSI Approved :: MIT License
Classifier: Operating System :: OS Independent
Requires-Python: >=3.8
License-File: LICENSE
Requires-Dist: pyautogui
Requires-Dist: pynput
Requires-Dist: ttkthemes
